<?xml version="1.0" encoding="utf-8" ?>
<dwsync>
<file name="logo.png" server="218.234.17.178//website/망고게임/" local="130891923000000000" remote="130891923000000000" />
<file name="menu.png" server="218.234.17.178//website/망고게임/" local="130891933800000000" remote="130891933800000000" />
<file name="passmain_gold.jpg" server="218.234.17.178//website/망고게임/" local="130891936200000000" remote="130891936200000000" />
<file name="passmain_gold_info.gif" server="218.234.17.178//website/망고게임/" local="130891936200000000" remote="130891936200000000" />
<file name="passmain_gold_info.jpg" server="218.234.17.178//website/망고게임/" local="130891936200000000" remote="130891936200000000" />
<file name="passmain_tab.jpg" server="218.234.17.178//website/망고게임/" local="130891936200000000" remote="130891936200000000" />
<file name="pass_gold.jpg" server="218.234.17.178//website/망고게임/" local="130891936200000000" remote="130891936200000000" />
<file name="visual.jpg" server="218.234.17.178//website/망고게임/" local="130891924200000000" remote="130891924200000000" />
</dwsync>